{
 "PRed":[
  {
   "PR":{
    "__lazy_json__":"pr_json/220973124.json"
   },
   "data":{
    "bot_rerun":false,
    "migrator_name":"CompilerRebuild",
    "migrator_version":1,
    "name":"Python 3.7, GCC 7, R 3.5.1, openBLAS 0.3.2"
   },
   "keys":[
    "bot_rerun",
    "migrator_name",
    "migrator_version",
    "name"
   ]
  },
  {
   "PR":{
    "__lazy_json__":"pr_json/285610691.json"
   },
   "data":{
    "bot_rerun":false,
    "migrator_name":"Rebuild",
    "migrator_version":0,
    "name":"hdf5-1.10.5"
   },
   "keys":[
    "bot_rerun",
    "migrator_name",
    "migrator_version",
    "name"
   ]
  }
 ],
 "bad":false,
 "conda-forge.yml":{
  "compiler_stack":"comp7",
  "max_py_ver":"37",
  "max_r_ver":"35",
  "provider":{
   "win":"azure"
  }
 },
 "feedstock_name":"kealib",
 "hash_type":"sha256",
 "meta_yaml":{
  "about":{
   "home":"http://kealib.org/",
   "license":"MIT",
   "license_file":"LICENSE.txt",
   "summary":"The KEA format provides an implementation of the GDAL specification within the the HDF5 file format."
  },
  "build":{
   "number":"0",
   "run_exports":[
    "subpackage_stub",
    "subpackage_stub",
    "subpackage_stub"
   ],
   "skip":true
  },
  "extra":{
   "recipe-maintainers":[
    "gillins",
    "danclewley",
    "gillins",
    "danclewley",
    "gillins",
    "danclewley"
   ]
  },
  "package":{
   "name":"kealib",
   "version":"1.4.12"
  },
  "requirements":{
   "build":[
    "c_compiler_stub",
    "cxx_compiler_stub",
    "cmake",
    "c_compiler_stub",
    "cxx_compiler_stub",
    "cmake",
    "make",
    "c_compiler_stub",
    "cxx_compiler_stub",
    "cmake",
    "make"
   ],
   "host":[
    "hdf5",
    "hdf5",
    "hdf5"
   ],
   "run":[
    "hdf5",
    "hdf5",
    "hdf5"
   ]
  },
  "source":{
   "sha256":"0b100e36b3e25e57487aa197d7be47f22e1b30afb16a57fdaa5f877696ec321e",
   "url":"https://github.com/ubarsc/kealib/releases/download/kealib-1.4.12/kealib-1.4.12.tar.gz"
  },
  "test":{
   "commands":[
    "gdal_translate --formats",
    "gdal_translate --formats",
    "gdal_translate --formats"
   ],
   "requires":[
    "libgdal",
    "libgdal",
    "libgdal"
   ]
  }
 },
 "name":"kealib",
 "new_version":false,
 "pinning_version":"2019.06.05",
 "raw_meta_yaml":"{% set version = \"1.4.12\" %}\n\npackage:\n  name: kealib\n  version: {{ version }}\n\nsource:\n  url: https://github.com/ubarsc/kealib/releases/download/kealib-{{ version }}/kealib-{{ version }}.tar.gz\n  sha256: 0b100e36b3e25e57487aa197d7be47f22e1b30afb16a57fdaa5f877696ec321e\n\nbuild:\n  number: 0\n  skip: True  # [win and vc<14]\n  run_exports:\n    - {{ pin_subpackage('kealib', max_pin='x.x') }}\n\nrequirements:\n  build:\n    - {{ compiler('c') }}\n    - {{ compiler('cxx') }}\n    - cmake\n    - make  # [unix]\n  host:\n    - hdf5\n  run:\n    - hdf5\n\ntest:\n  requires:\n    - libgdal\n  commands:\n    # check we haven't broken GDAL\n    - gdal_translate --formats\n\nabout:\n  home: http://kealib.org/\n  license: MIT\n  license_file: LICENSE.txt\n  summary: The KEA format provides an implementation of the GDAL specification within the the HDF5 file format.\n\nextra:\n  recipe-maintainers:\n    - gillins\n    - danclewley\n",
 "req":{
  "__set__":true,
  "elements":[
   "c_compiler_stub",
   "cmake",
   "cxx_compiler_stub",
   "hdf5",
   "make"
  ]
 },
 "requirements":{
  "build":{
   "__set__":true,
   "elements":[
    "c_compiler_stub",
    "cmake",
    "cxx_compiler_stub",
    "make"
   ]
  },
  "host":{
   "__set__":true,
   "elements":[
    "hdf5"
   ]
  },
  "run":{
   "__set__":true,
   "elements":[
    "hdf5"
   ]
  },
  "test":{
   "__set__":true,
   "elements":[
    "libgdal"
   ]
  }
 },
 "smithy_version":"3.3.6",
 "strong_exports":false,
 "total_requirements":{
  "build":{
   "__set__":true,
   "elements":[
    "c_compiler_stub",
    "cmake",
    "cxx_compiler_stub",
    "make"
   ]
  },
  "host":{
   "__set__":true,
   "elements":[
    "hdf5"
   ]
  },
  "run":{
   "__set__":true,
   "elements":[
    "hdf5"
   ]
  },
  "test":{
   "__set__":true,
   "elements":[
    "libgdal"
   ]
  }
 },
 "url":"https://bitbucket.org/chchrsc/kealib/downloads/kealib-1.4.10.tar.gz",
 "version":"1.4.12"
}