{
 "PRed":[
  {
   "PR":{
    "__lazy_json__":"pr_json/242388291.json"
   },
   "data":{
    "bot_rerun":false,
    "migrator_name":"CompilerRebuild",
    "migrator_version":1,
    "name":"Python 3.7, GCC 7, R 3.5.1, openBLAS 0.3.2"
   },
   "keys":[
    "bot_rerun",
    "migrator_name",
    "migrator_version",
    "name"
   ]
  },
  {
   "PR":{
    "__lazy_json__":"pr_json/256927964.json"
   },
   "data":{
    "bot_rerun":false,
    "migrator_name":"Version",
    "migrator_version":0,
    "version":"6.23.0"
   },
   "keys":[
    "bot_rerun",
    "migrator_name",
    "migrator_version",
    "version"
   ]
  },
  {
   "PR":{
    "__lazy_json__":"pr_json/281862766.json"
   },
   "data":{
    "bot_rerun":false,
    "migrator_name":"Version",
    "migrator_version":0,
    "version":"6.24.0"
   },
   "keys":[
    "bot_rerun",
    "migrator_name",
    "migrator_version",
    "version"
   ]
  },
  {
   "PR":{
    "__lazy_json__":"pr_json/296130138.json"
   },
   "data":{
    "bot_rerun":false,
    "migrator_name":"Rebuild",
    "migrator_version":0,
    "name":"gsl-2.5"
   },
   "keys":[
    "bot_rerun",
    "migrator_name",
    "migrator_version",
    "name"
   ]
  },
  {
   "PR":{
    "__lazy_json__":"pr_json/298180427.json"
   },
   "data":{
    "bot_rerun":false,
    "migrator_name":"Rebuild",
    "migrator_version":0,
    "name":"cfitsio-3.470"
   },
   "keys":[
    "bot_rerun",
    "migrator_name",
    "migrator_version",
    "name"
   ]
  },
  {
   "PR":{
    "__lazy_json__":"pr_json/345731245.json"
   },
   "data":{
    "bot_rerun":false,
    "migrator_name":"MigrationYaml",
    "migrator_object_version":1,
    "migrator_version":0,
    "name":"python38"
   },
   "keys":[
    "bot_rerun",
    "migrator_name",
    "migrator_object_version",
    "migrator_version",
    "name"
   ]
  }
 ],
 "bad":false,
 "conda-forge.yml":{
  "compiler_stack":"comp7",
  "max_py_ver":"37",
  "max_r_ver":"35"
 },
 "feedstock_name":"lalapps",
 "hash_type":"sha256",
 "meta_yaml":{
  "about":{
   "description":"The LSC Algorithm Library Applications for gravitational wave data\nanalysis.  This package contains applications that are built on tools\nin the LSC Algorithm Library.\n",
   "dev_url":"https://git.ligo.org/lscsoft/lalsuite/",
   "doc_url":"https://docs.ligo.org/lscsoft/lalsuite/lalapps/",
   "home":"https://wiki.ligo.org/Computing/DASWG/LALSuite",
   "license":"GPLv3",
   "license_family":"GPL",
   "license_file":"COPYING",
   "summary":"LSC Algorithm Library Applications"
  },
  "build":{
   "error_overdepending":true,
   "error_overlinking":true,
   "ignore_run_exports":[
    "fftw",
    "fftw",
    "fftw"
   ],
   "number":"3",
   "skip":true
  },
  "extra":{
   "recipe-maintainers":[
    "duncanmmacleod",
    "skymoo",
    "duncanmmacleod",
    "skymoo",
    "duncanmmacleod",
    "skymoo"
   ]
  },
  "package":{
   "name":"lalapps",
   "version":"6.24.0"
  },
  "requirements":{
   "build":[
    "c_compiler_stub",
    "make",
    "pkg-config",
    "c_compiler_stub",
    "make",
    "pkg-config",
    "c_compiler_stub",
    "make",
    "pkg-config"
   ],
   "host":[
    "cfitsio",
    "fftw * nompi*",
    "gsl",
    "lal >=6.20.0",
    "lalburst >=1.5.1",
    "lalframe >=1.4.0",
    "lalinference >=1.11.0",
    "lalinspiral >=1.9.0",
    "lalmetaio >=1.5.0",
    "lalpulsar >=1.18.0",
    "lalsimulation >=1.9.0",
    "libframe",
    "metaio",
    "openmpi",
    "python",
    "python-lal >=6.20.0",
    "python-lalburst >=1.5.1",
    "python-lalinference >=1.11.0",
    "python-lalinspiral >=1.9.0",
    "python-lalframe >=1.4.0",
    "python-lalmetaio >=1.5.0",
    "python-lalpulsar >=1.18.0",
    "python-lalsimulation >=1.9.0",
    "cfitsio",
    "fftw * nompi*",
    "gsl",
    "lal >=6.20.0",
    "lalburst >=1.5.1",
    "lalframe >=1.4.0",
    "lalinference >=1.11.0",
    "lalinspiral >=1.9.0",
    "lalmetaio >=1.5.0",
    "lalpulsar >=1.18.0",
    "lalsimulation >=1.9.0",
    "libframe",
    "llvm-openmp",
    "metaio",
    "openmpi",
    "python",
    "python-lal >=6.20.0",
    "python-lalburst >=1.5.1",
    "python-lalinference >=1.11.0",
    "python-lalinspiral >=1.9.0",
    "python-lalframe >=1.4.0",
    "python-lalmetaio >=1.5.0",
    "python-lalpulsar >=1.18.0",
    "python-lalsimulation >=1.9.0",
    "cfitsio",
    "fftw * nompi*",
    "gsl",
    "lal >=6.20.0",
    "lalburst >=1.5.1",
    "lalframe >=1.4.0",
    "lalinference >=1.11.0",
    "lalinspiral >=1.9.0",
    "lalmetaio >=1.5.0",
    "lalpulsar >=1.18.0",
    "lalsimulation >=1.9.0",
    "libframe",
    "metaio",
    "openmp",
    "openmpi",
    "python",
    "python-lal >=6.20.0",
    "python-lalburst >=1.5.1",
    "python-lalinference >=1.11.0",
    "python-lalinspiral >=1.9.0",
    "python-lalframe >=1.4.0",
    "python-lalmetaio >=1.5.0",
    "python-lalpulsar >=1.18.0",
    "python-lalsimulation >=1.9.0"
   ],
   "run":[
    "cfitsio",
    "fftw",
    "gsl",
    "h5py",
    "healpy",
    "lal >=6.20.0",
    "lalframe >=1.4.0",
    "lalmetaio >=1.5.0",
    "lalsimulation >=1.9.0",
    "lalburst >=1.5.1",
    "lalinspiral >=1.9.0",
    "lalpulsar >=1.18.0",
    "lalinference >=1.11.0",
    "libframe",
    "ligo-segments",
    "metaio",
    "openmpi",
    "numpy",
    "pillow",
    "python",
    "python-lal >=6.20.0",
    "python-lalburst >=1.5.1",
    "python-lalframe >=1.4.0",
    "python-lalinference >=1.11.0",
    "python-lalinspiral >=1.9.0",
    "python-lalmetaio >=1.5.0",
    "python-lalpulsar >=1.18.0",
    "python-lalsimulation >=1.9.0",
    "cfitsio",
    "fftw",
    "gsl",
    "h5py",
    "healpy",
    "lal >=6.20.0",
    "lalframe >=1.4.0",
    "lalmetaio >=1.5.0",
    "lalsimulation >=1.9.0",
    "lalburst >=1.5.1",
    "lalinspiral >=1.9.0",
    "lalpulsar >=1.18.0",
    "lalinference >=1.11.0",
    "libframe",
    "ligo-segments",
    "llvm-openmp",
    "metaio",
    "openmpi",
    "numpy",
    "pillow",
    "python",
    "python-lal >=6.20.0",
    "python-lalburst >=1.5.1",
    "python-lalframe >=1.4.0",
    "python-lalinference >=1.11.0",
    "python-lalinspiral >=1.9.0",
    "python-lalmetaio >=1.5.0",
    "python-lalpulsar >=1.18.0",
    "python-lalsimulation >=1.9.0",
    "cfitsio",
    "fftw",
    "gsl",
    "h5py",
    "healpy",
    "lal >=6.20.0",
    "lalframe >=1.4.0",
    "lalmetaio >=1.5.0",
    "lalsimulation >=1.9.0",
    "lalburst >=1.5.1",
    "lalinspiral >=1.9.0",
    "lalpulsar >=1.18.0",
    "lalinference >=1.11.0",
    "libframe",
    "ligo-segments",
    "metaio",
    "openmp",
    "openmpi",
    "numpy",
    "pillow",
    "python",
    "python-lal >=6.20.0",
    "python-lalburst >=1.5.1",
    "python-lalframe >=1.4.0",
    "python-lalinference >=1.11.0",
    "python-lalinspiral >=1.9.0",
    "python-lalmetaio >=1.5.0",
    "python-lalpulsar >=1.18.0",
    "python-lalsimulation >=1.9.0"
   ]
  },
  "source":{
   "fn":"lalapps-6.24.0.tar.xz",
   "patches":[
    "disable-weave-tests.patch",
    "disable-weave-tests.patch",
    "disable-weave-tests.patch"
   ],
   "sha256":"6db6c4368d548eeb3adb486dd4c6ec7bf4aeae33b7094fbee2cbbf1e2bc8db22",
   "url":"http://software.ligo.org/lscsoft/source/lalsuite/lalapps-6.24.0.tar.xz"
  },
  "test":{
   "commands":[
    "lalapps_version --help",
    "lalapps_binj --help",
    "lalapps_binjfind --help",
    "lalapps_binj_pic --help",
    "lalapps_blindinj --help",
    "lalapps_bucluster --help",
    "lalapps_bucut --help",
    "lalapps_burca --help",
    "lalapps_burca_tailor --help",
    "lalapps_cafe --help",
    "lalapps_calcexpsnr --help",
    "lalapps_coh_PTF_inspiral --help",
    "lalapps_coinj --help",
    "lalapps_create_pulsar_signal_frame --help",
    "lalapps_create_solar_system_ephemeris --help",
    "lalapps_create_solar_system_ephemeris_python --help",
    "lalapps_effdist --help",
    "lalapps_fftwf_wisdom --help",
    "lalapps_fftw_wisdom --help",
    "lalapps_fits_array_copy --help",
    "lalapps_fits_array_imarith --help",
    "lalapps_fits_array_list --help",
    "lalapps_fits_array_stat --help",
    "lalapps_fits_copy --help",
    "lalapps_fits_header_delval --help",
    "lalapps_fits_header_getval --help",
    "lalapps_fits_header_list --help",
    "lalapps_fits_header_setval --help",
    "lalapps_fits_overview --help",
    "lalapps_fits_table_calc --help",
    "lalapps_fits_table_list --help",
    "lalapps_fits_table_merge --help",
    "lalapps_fits_table_select --help",
    "lalapps_flag_triggers --help",
    "lalapps_frjoin --help",
    "lalapps_fr_ninja --help",
    "lalapps_frview --help",
    "lalapps_generate_upper_limits --help",
    "lalapps_gen_timeslides --help",
    "lalapps_gwf2xml --help",
    "lalapps_heterodyne_pulsar --help",
    "lalapps_inspfrinj --help",
    "lalapps_inspinj --help",
    "lalapps_inspinjfind --help",
    "lalapps_makeblindinj --help",
    "lalapps_makeblindinj_himass --help",
    "lalapps_make_nr_hdf_catalog --help",
    "lalapps_MakeSFTs --help",
    "lalapps_mdc_ninja --help",
    "lalapps_NoiseComparison --help",
    "lalapps_online_datafind --help",
    "lalapps_path2cache --help",
    "lalapps_plot_tisi --help",
    "lalapps_power --help",
    "lalapps_power_calc_likelihood --help",
    "lalapps_power_final --help",
    "lalapps_power_plot_binj --help",
    "lalapps_power_plot_binjtf --help",
    "lalapps_power_plot_burca --help",
    "lalapps_power_plot_burca2 --help",
    "lalapps_power_plot_burst --help",
    "lalapps_power_veto --help",
    "lalapps_pulsar_frequency_evolution --help",
    "lalapps_pulsar_parameter_estimation --help",
    "lalapps_pulsar_parameter_estimation_nested --help",
    "lalapps_randombank --help",
    "lalapps_run_sqlite --help",
    "lalapps_searchsum2cache --help",
    "lalapps_SFTwrite --help",
    "lalapps_siva --help",
    "lalapps_splitSFTs --help",
    "lalapps_ssbtodetector --help",
    "lalapps_string_apply_vetoes --help",
    "lalapps_string_calc_likelihood --help",
    "lalapps_string_contour_plotter --help",
    "lalapps_string_cs_gamma --help",
    "lalapps_string_meas_likelihood --help",
    "lalapps_string_plot_binj --help",
    "lalapps_string_plot_likelihood --help",
    "lalapps_StringSearch --help",
    "lalapps_tconvert --help",
    "lalapps_thinca --help",
    "lalapps_tmpltbank --help",
    "lalapps_version --help",
    "lalapps_binj --help",
    "lalapps_binjfind --help",
    "lalapps_binj_pic --help",
    "lalapps_blindinj --help",
    "lalapps_bucluster --help",
    "lalapps_bucut --help",
    "lalapps_burca --help",
    "lalapps_burca_tailor --help",
    "lalapps_cafe --help",
    "lalapps_calcexpsnr --help",
    "lalapps_coh_PTF_inspiral --help",
    "lalapps_coinj --help",
    "lalapps_create_pulsar_signal_frame --help",
    "lalapps_create_solar_system_ephemeris --help",
    "lalapps_create_solar_system_ephemeris_python --help",
    "lalapps_effdist --help",
    "lalapps_fftwf_wisdom --help",
    "lalapps_fftw_wisdom --help",
    "lalapps_fits_array_copy --help",
    "lalapps_fits_array_imarith --help",
    "lalapps_fits_array_list --help",
    "lalapps_fits_array_stat --help",
    "lalapps_fits_copy --help",
    "lalapps_fits_header_delval --help",
    "lalapps_fits_header_getval --help",
    "lalapps_fits_header_list --help",
    "lalapps_fits_header_setval --help",
    "lalapps_fits_overview --help",
    "lalapps_fits_table_calc --help",
    "lalapps_fits_table_list --help",
    "lalapps_fits_table_merge --help",
    "lalapps_fits_table_select --help",
    "lalapps_flag_triggers --help",
    "lalapps_frjoin --help",
    "lalapps_fr_ninja --help",
    "lalapps_frview --help",
    "lalapps_generate_upper_limits --help",
    "lalapps_gen_timeslides --help",
    "lalapps_gwf2xml --help",
    "lalapps_heterodyne_pulsar --help",
    "lalapps_inspfrinj --help",
    "lalapps_inspinj --help",
    "lalapps_inspinjfind --help",
    "lalapps_makeblindinj --help",
    "lalapps_makeblindinj_himass --help",
    "lalapps_make_nr_hdf_catalog --help",
    "lalapps_MakeSFTs --help",
    "lalapps_mdc_ninja --help",
    "lalapps_NoiseComparison --help",
    "lalapps_online_datafind --help",
    "lalapps_path2cache --help",
    "lalapps_plot_tisi --help",
    "lalapps_power --help",
    "lalapps_power_calc_likelihood --help",
    "lalapps_power_final --help",
    "lalapps_power_plot_binj --help",
    "lalapps_power_plot_binjtf --help",
    "lalapps_power_plot_burca --help",
    "lalapps_power_plot_burca2 --help",
    "lalapps_power_plot_burst --help",
    "lalapps_power_veto --help",
    "lalapps_pulsar_frequency_evolution --help",
    "lalapps_pulsar_parameter_estimation --help",
    "lalapps_pulsar_parameter_estimation_nested --help",
    "lalapps_randombank --help",
    "lalapps_run_sqlite --help",
    "lalapps_searchsum2cache --help",
    "lalapps_SFTwrite --help",
    "lalapps_siva --help",
    "lalapps_splitSFTs --help",
    "lalapps_ssbtodetector --help",
    "lalapps_string_apply_vetoes --help",
    "lalapps_string_calc_likelihood --help",
    "lalapps_string_contour_plotter --help",
    "lalapps_string_cs_gamma --help",
    "lalapps_string_meas_likelihood --help",
    "lalapps_string_plot_binj --help",
    "lalapps_string_plot_likelihood --help",
    "lalapps_StringSearch --help",
    "lalapps_tconvert --help",
    "lalapps_thinca --help",
    "lalapps_tmpltbank --help",
    "lalapps_version --help",
    "lalapps_binj --help",
    "lalapps_binjfind --help",
    "lalapps_binj_pic --help",
    "lalapps_blindinj --help",
    "lalapps_bucluster --help",
    "lalapps_bucut --help",
    "lalapps_burca --help",
    "lalapps_burca_tailor --help",
    "lalapps_cafe --help",
    "lalapps_calcexpsnr --help",
    "lalapps_coh_PTF_inspiral --help",
    "lalapps_coinj --help",
    "lalapps_create_pulsar_signal_frame --help",
    "lalapps_create_solar_system_ephemeris --help",
    "lalapps_create_solar_system_ephemeris_python --help",
    "lalapps_effdist --help",
    "lalapps_fftwf_wisdom --help",
    "lalapps_fftw_wisdom --help",
    "lalapps_fits_array_copy --help",
    "lalapps_fits_array_imarith --help",
    "lalapps_fits_array_list --help",
    "lalapps_fits_array_stat --help",
    "lalapps_fits_copy --help",
    "lalapps_fits_header_delval --help",
    "lalapps_fits_header_getval --help",
    "lalapps_fits_header_list --help",
    "lalapps_fits_header_setval --help",
    "lalapps_fits_overview --help",
    "lalapps_fits_table_calc --help",
    "lalapps_fits_table_list --help",
    "lalapps_fits_table_merge --help",
    "lalapps_fits_table_select --help",
    "lalapps_flag_triggers --help",
    "lalapps_frjoin --help",
    "lalapps_fr_ninja --help",
    "lalapps_frview --help",
    "lalapps_generate_upper_limits --help",
    "lalapps_gen_timeslides --help",
    "lalapps_gwf2xml --help",
    "lalapps_heterodyne_pulsar --help",
    "lalapps_inspfrinj --help",
    "lalapps_inspinj --help",
    "lalapps_inspinjfind --help",
    "lalapps_makeblindinj --help",
    "lalapps_makeblindinj_himass --help",
    "lalapps_make_nr_hdf_catalog --help",
    "lalapps_MakeSFTs --help",
    "lalapps_mdc_ninja --help",
    "lalapps_NoiseComparison --help",
    "lalapps_online_datafind --help",
    "lalapps_path2cache --help",
    "lalapps_plot_tisi --help",
    "lalapps_power --help",
    "lalapps_power_calc_likelihood --help",
    "lalapps_power_final --help",
    "lalapps_power_plot_binj --help",
    "lalapps_power_plot_binjtf --help",
    "lalapps_power_plot_burca --help",
    "lalapps_power_plot_burca2 --help",
    "lalapps_power_plot_burst --help",
    "lalapps_power_veto --help",
    "lalapps_pulsar_frequency_evolution --help",
    "lalapps_pulsar_parameter_estimation --help",
    "lalapps_pulsar_parameter_estimation_nested --help",
    "lalapps_randombank --help",
    "lalapps_run_sqlite --help",
    "lalapps_searchsum2cache --help",
    "lalapps_SFTwrite --help",
    "lalapps_siva --help",
    "lalapps_splitSFTs --help",
    "lalapps_ssbtodetector --help",
    "lalapps_string_apply_vetoes --help",
    "lalapps_string_calc_likelihood --help",
    "lalapps_string_contour_plotter --help",
    "lalapps_string_cs_gamma --help",
    "lalapps_string_meas_likelihood --help",
    "lalapps_string_plot_binj --help",
    "lalapps_string_plot_likelihood --help",
    "lalapps_StringSearch --help",
    "lalapps_tconvert --help",
    "lalapps_thinca --help",
    "lalapps_tmpltbank --help"
   ],
   "imports":[
    "lalapps",
    "lalapps.git_version",
    "lalapps",
    "lalapps.git_version",
    "lalapps",
    "lalapps.git_version"
   ]
  }
 },
 "name":"lalapps",
 "new_version":false,
 "pinning_version":"2019.11.26",
 "raw_meta_yaml":"{% set name = \"lalapps\" %}\n{% set version = \"6.24.0\" %}\n{% set sha256 = \"6db6c4368d548eeb3adb486dd4c6ec7bf4aeae33b7094fbee2cbbf1e2bc8db22\" %}\n\n{% set lal_version = \"6.20.0\" %}\n{% set lalburst_version = \"1.5.1\" %}\n{% set lalframe_version = \"1.4.0\" %}\n{% set lalinference_version = \"1.11.0\" %}\n{% set lalinspiral_version = \"1.9.0\" %}\n{% set lalmetaio_version = \"1.5.0\" %}\n{% set lalpulsar_version = \"1.18.0\" %}\n{% set lalsimulation_version = \"1.9.0\" %}\n\npackage:\n  name: {{ name }}\n  version: {{ version }}\n\nsource:\n  fn: {{ name }}-{{ version }}.tar.xz\n  url: http://software.ligo.org/lscsoft/source/lalsuite/{{ name }}-{{ version }}.tar.xz\n  sha256: {{ sha256 }}\n  patches:\n    # weave tests are fragile and hardware dependent\n    - disable-weave-tests.patch\n\nbuild:\n  error_overdepending: true\n  error_overlinking: true\n  ignore_run_exports:\n    # run_exports parsing for fftw is broken, so we ignore it\n    # manually, for now\n    - fftw\n  number: 3\n  skip: true  # [win]\n\nrequirements:\n  build:\n    - {{ compiler('c') }}\n    - make\n    - pkg-config\n  host:\n    - cfitsio\n    - fftw * nompi*\n    - gsl\n    - lal >={{ lal_version }}\n    - lalburst >={{ lalburst_version }}\n    - lalframe >={{ lalframe_version }}\n    - lalinference >={{ lalinference_version }}\n    - lalinspiral >={{ lalinspiral_version }}\n    - lalmetaio >={{ lalmetaio_version }}\n    - lalpulsar >={{ lalpulsar_version }}\n    - lalsimulation >={{ lalsimulation_version }}\n    - libframe\n    - llvm-openmp  # [osx]\n    - metaio\n    - openmp  # [linux]\n    - openmpi\n    - python\n    - python-lal >={{ lal_version }}\n    - python-lalburst >={{ lalburst_version }}\n    - python-lalinference >={{ lalinference_version }}\n    - python-lalinspiral >={{ lalinspiral_version }}\n    - python-lalframe >={{ lalframe_version }}\n    - python-lalmetaio >={{ lalmetaio_version }}\n    - python-lalpulsar >={{ lalpulsar_version }}\n    - python-lalsimulation >={{ lalsimulation_version }}\n  run:\n    - cfitsio\n    - fftw\n    - gsl\n    - h5py\n    - healpy\n    - lal >={{ lal_version }}\n    - lalframe >={{ lalframe_version }}\n    - lalmetaio >={{ lalmetaio_version }}\n    - lalsimulation >={{ lalsimulation_version }}\n    - lalburst >={{ lalburst_version }}\n    - lalinspiral >={{ lalinspiral_version }}\n    - lalpulsar >={{ lalpulsar_version }}\n    - lalinference >={{ lalinference_version }}\n    - libframe\n    - ligo-segments\n    - llvm-openmp  # [osx]\n    - metaio\n    - openmp  # [linux]\n    - openmpi\n    - numpy\n    - pillow\n    - python\n    - python-lal >={{ lal_version }}\n    - python-lalburst >={{ lalburst_version }}\n    - python-lalframe >={{ lalframe_version }}\n    - python-lalinference >={{ lalinference_version }}\n    - python-lalinspiral >={{ lalinspiral_version }}\n    - python-lalmetaio >={{ lalmetaio_version }}\n    - python-lalpulsar >={{ lalpulsar_version }}\n    - python-lalsimulation >={{ lalsimulation_version }}\n\ntest:\n  imports:\n    - lalapps\n    - lalapps.git_version\n  commands:\n    - lalapps_version --help\n    - lalapps_binj --help\n    - lalapps_binjfind --help\n    - lalapps_binj_pic --help\n    - lalapps_blindinj --help\n    - lalapps_bucluster --help\n    - lalapps_bucut --help\n    - lalapps_burca --help\n    - lalapps_burca_tailor --help\n    - lalapps_cafe --help\n    - lalapps_calcexpsnr --help\n    - lalapps_coh_PTF_inspiral --help\n    - lalapps_coinj --help\n    - lalapps_create_pulsar_signal_frame --help\n    - lalapps_create_solar_system_ephemeris --help\n    - lalapps_create_solar_system_ephemeris_python --help\n    - lalapps_effdist --help\n    - lalapps_fftwf_wisdom --help\n    - lalapps_fftw_wisdom --help\n    - lalapps_fits_array_copy --help\n    - lalapps_fits_array_imarith --help\n    - lalapps_fits_array_list --help\n    - lalapps_fits_array_stat --help\n    - lalapps_fits_copy --help\n    - lalapps_fits_header_delval --help\n    - lalapps_fits_header_getval --help\n    - lalapps_fits_header_list --help\n    - lalapps_fits_header_setval --help\n    - lalapps_fits_overview --help\n    - lalapps_fits_table_calc --help\n    - lalapps_fits_table_list --help\n    - lalapps_fits_table_merge --help\n    - lalapps_fits_table_select --help\n    - lalapps_flag_triggers --help\n    - lalapps_frjoin --help\n    - lalapps_fr_ninja --help\n    - lalapps_frview --help\n    - lalapps_generate_upper_limits --help\n    - lalapps_gen_timeslides --help\n    - lalapps_gwf2xml --help\n    - lalapps_heterodyne_pulsar --help\n    - lalapps_inspfrinj --help\n    - lalapps_inspinj --help\n    - lalapps_inspinjfind --help\n    - lalapps_makeblindinj --help\n    - lalapps_makeblindinj_himass --help\n    - lalapps_make_nr_hdf_catalog --help\n    - lalapps_MakeSFTs --help\n    - lalapps_mdc_ninja --help\n    - lalapps_NoiseComparison --help\n    - lalapps_online_datafind --help\n    - lalapps_path2cache --help\n    - lalapps_plot_tisi --help\n    - lalapps_power --help\n    - lalapps_power_calc_likelihood --help\n    - lalapps_power_final --help\n    - lalapps_power_plot_binj --help\n    - lalapps_power_plot_binjtf --help\n    - lalapps_power_plot_burca --help\n    - lalapps_power_plot_burca2 --help\n    - lalapps_power_plot_burst --help\n    - lalapps_power_veto --help\n    - lalapps_pulsar_frequency_evolution --help\n    - lalapps_pulsar_parameter_estimation --help\n    - lalapps_pulsar_parameter_estimation_nested --help\n    - lalapps_randombank --help\n    - lalapps_run_sqlite --help\n    - lalapps_searchsum2cache --help\n    - lalapps_SFTwrite --help\n    - lalapps_siva --help\n    - lalapps_splitSFTs --help\n    - lalapps_ssbtodetector --help\n    - lalapps_string_apply_vetoes --help\n    - lalapps_string_calc_likelihood --help\n    - lalapps_string_contour_plotter --help\n    - lalapps_string_cs_gamma --help\n    - lalapps_string_meas_likelihood --help\n    - lalapps_string_plot_binj --help\n    - lalapps_string_plot_likelihood --help\n    - lalapps_StringSearch --help\n    - lalapps_tconvert --help\n    - lalapps_thinca --help\n    - lalapps_tmpltbank --help\n\nabout:\n  home: https://wiki.ligo.org/Computing/DASWG/LALSuite\n  doc_url: https://docs.ligo.org/lscsoft/lalsuite/lalapps/\n  dev_url: https://git.ligo.org/lscsoft/lalsuite/\n  license: GPLv3\n  license_family: GPL\n  license_file: COPYING\n  summary: LSC Algorithm Library Applications\n  description: |\n    The LSC Algorithm Library Applications for gravitational wave data\n    analysis.  This package contains applications that are built on tools\n    in the LSC Algorithm Library.\n\nextra:\n  recipe-maintainers:\n    - duncanmmacleod\n    - skymoo\n",
 "req":{
  "__set__":true,
  "elements":[
   "c_compiler_stub",
   "cfitsio",
   "fftw",
   "gsl",
   "h5py",
   "healpy",
   "lal",
   "lalburst",
   "lalframe",
   "lalinference",
   "lalinspiral",
   "lalmetaio",
   "lalpulsar",
   "lalsimulation",
   "libframe",
   "ligo-segments",
   "llvm-openmp",
   "make",
   "metaio",
   "numpy",
   "openmp",
   "openmpi",
   "pillow",
   "pkg-config",
   "python",
   "python-lal",
   "python-lalburst",
   "python-lalframe",
   "python-lalinference",
   "python-lalinspiral",
   "python-lalmetaio",
   "python-lalpulsar",
   "python-lalsimulation"
  ]
 },
 "smithy_version":"3.6.2",
 "url":"http://software.ligo.org/lscsoft/source/lalsuite/lalapps-6.24.0.tar.xz",
 "version":"6.24.0"
}