{
 "PRed":[
  {
   "data":{
    "bot_rerun":false,
    "migrator_name":"Version",
    "migrator_version":0,
    "version":"0.23.2"
   },
   "keys":[
    "bot_rerun",
    "migrator_name",
    "migrator_version",
    "version"
   ]
  },
  {
   "PR":{
    "__lazy_json__":"pr_json/200480828.json"
   },
   "data":{
    "bot_rerun":false,
    "migrator_name":"Version",
    "migrator_version":0,
    "version":"0.24.0"
   },
   "keys":[
    "bot_rerun",
    "migrator_name",
    "migrator_version",
    "version"
   ]
  },
  {
   "PR":{
    "__lazy_json__":"pr_json/217391771.json"
   },
   "data":{
    "bot_rerun":false,
    "migrator_name":"Version",
    "migrator_version":0,
    "version":"0.25.0"
   },
   "keys":[
    "bot_rerun",
    "migrator_name",
    "migrator_version",
    "version"
   ]
  },
  {
   "PR":{
    "__lazy_json__":"pr_json/220717073.json"
   },
   "data":{
    "bot_rerun":false,
    "migrator_name":"CompilerRebuild",
    "migrator_version":1,
    "name":"Python 3.7, GCC 7, R 3.5.1, openBLAS 0.3.2"
   },
   "keys":[
    "bot_rerun",
    "migrator_name",
    "migrator_version",
    "name"
   ]
  },
  {
   "PR":{
    "__lazy_json__":"pr_json/234314339.json"
   },
   "data":{
    "bot_rerun":false,
    "migrator_name":"Version",
    "migrator_version":0,
    "version":"0.26.0"
   },
   "keys":[
    "bot_rerun",
    "migrator_name",
    "migrator_version",
    "version"
   ]
  },
  {
   "PR":{
    "__lazy_json__":"pr_json/241597735.json"
   },
   "data":{
    "bot_rerun":false,
    "migrator_name":"Version",
    "migrator_version":0,
    "version":"0.27.0"
   },
   "keys":[
    "bot_rerun",
    "migrator_name",
    "migrator_version",
    "version"
   ]
  },
  {
   "PR":{
    "__lazy_json__":"pr_json/260505164.json"
   },
   "data":{
    "bot_rerun":false,
    "migrator_name":"Version",
    "migrator_version":0,
    "version":"0.27.1"
   },
   "keys":[
    "bot_rerun",
    "migrator_name",
    "migrator_version",
    "version"
   ]
  },
  {
   "PR":{
    "__lazy_json__":"pr_json/260945847.json"
   },
   "data":{
    "bot_rerun":false,
    "migrator_name":"Version",
    "migrator_version":0,
    "version":"0.28.0"
   },
   "keys":[
    "bot_rerun",
    "migrator_name",
    "migrator_version",
    "version"
   ]
  },
  {
   "PR":{
    "__lazy_json__":"pr_json/283781896.json"
   },
   "data":{
    "bot_rerun":false,
    "migrator_name":"Version",
    "migrator_version":0,
    "version":"0.29.0"
   },
   "keys":[
    "bot_rerun",
    "migrator_name",
    "migrator_version",
    "version"
   ]
  },
  {
   "PR":{
    "__lazy_json__":"pr_json/292513535.json"
   },
   "data":{
    "bot_rerun":false,
    "migrator_name":"ArchRebuild",
    "migrator_version":1,
    "name":"aarch64 and ppc64le addition"
   },
   "keys":[
    "bot_rerun",
    "migrator_name",
    "migrator_version",
    "name"
   ]
  },
  {
   "PR":{
    "__lazy_json__":"pr_json/326911410.json"
   },
   "data":{
    "bot_rerun":false,
    "migrator_name":"Version",
    "migrator_version":0,
    "version":"0.30.0"
   },
   "keys":[
    "bot_rerun",
    "migrator_name",
    "migrator_version",
    "version"
   ]
  },
  {
   "PR":{
    "__lazy_json__":"pr_json/335622489.json"
   },
   "data":{
    "bot_rerun":false,
    "migrator_name":"MigrationYaml",
    "migrator_object_version":1,
    "migrator_version":0,
    "name":"python38"
   },
   "keys":[
    "bot_rerun",
    "migrator_name",
    "migrator_object_version",
    "migrator_version",
    "name"
   ]
  },
  {
   "PR":{
    "_links":{
     "comments":{
      "href":"https://api.github.com/repos/conda-forge/llvmlite-feedstock/issues/24/comments"
     },
     "commits":{
      "href":"https://api.github.com/repos/conda-forge/llvmlite-feedstock/pulls/24/commits"
     },
     "html":{
      "href":"https://github.com/conda-forge/llvmlite-feedstock/pull/24"
     },
     "issue":{
      "href":"https://api.github.com/repos/conda-forge/llvmlite-feedstock/issues/24"
     },
     "review_comment":{
      "href":"https://api.github.com/repos/conda-forge/llvmlite-feedstock/pulls/comments{/number}"
     },
     "review_comments":{
      "href":"https://api.github.com/repos/conda-forge/llvmlite-feedstock/pulls/24/comments"
     },
     "self":{
      "href":"https://api.github.com/repos/conda-forge/llvmlite-feedstock/pulls/24"
     },
     "statuses":{
      "href":"https://api.github.com/repos/conda-forge/llvmlite-feedstock/statuses/7c2612e82c3254f72de3003484d71c5640c6053f"
     }
    },
    "additions":5,
    "assignee":null,
    "assignees":[],
    "author_association":"CONTRIBUTOR",
    "base":{
     "label":"conda-forge:master",
     "ref":"master",
     "repo":{
      "archive_url":"https://api.github.com/repos/conda-forge/llvmlite-feedstock/{archive_format}{/ref}",
      "archived":false,
      "assignees_url":"https://api.github.com/repos/conda-forge/llvmlite-feedstock/assignees{/user}",
      "blobs_url":"https://api.github.com/repos/conda-forge/llvmlite-feedstock/git/blobs{/sha}",
      "branches_url":"https://api.github.com/repos/conda-forge/llvmlite-feedstock/branches{/branch}",
      "clone_url":"https://github.com/conda-forge/llvmlite-feedstock.git",
      "collaborators_url":"https://api.github.com/repos/conda-forge/llvmlite-feedstock/collaborators{/collaborator}",
      "comments_url":"https://api.github.com/repos/conda-forge/llvmlite-feedstock/comments{/number}",
      "commits_url":"https://api.github.com/repos/conda-forge/llvmlite-feedstock/commits{/sha}",
      "compare_url":"https://api.github.com/repos/conda-forge/llvmlite-feedstock/compare/{base}...{head}",
      "contents_url":"https://api.github.com/repos/conda-forge/llvmlite-feedstock/contents/{+path}",
      "contributors_url":"https://api.github.com/repos/conda-forge/llvmlite-feedstock/contributors",
      "created_at":"2017-12-12T15:59:40Z",
      "default_branch":"master",
      "deployments_url":"https://api.github.com/repos/conda-forge/llvmlite-feedstock/deployments",
      "description":"A conda-smithy repository for llvmlite.",
      "disabled":false,
      "downloads_url":"https://api.github.com/repos/conda-forge/llvmlite-feedstock/downloads",
      "events_url":"https://api.github.com/repos/conda-forge/llvmlite-feedstock/events",
      "fork":false,
      "forks":6,
      "forks_count":6,
      "forks_url":"https://api.github.com/repos/conda-forge/llvmlite-feedstock/forks",
      "full_name":"conda-forge/llvmlite-feedstock",
      "git_commits_url":"https://api.github.com/repos/conda-forge/llvmlite-feedstock/git/commits{/sha}",
      "git_refs_url":"https://api.github.com/repos/conda-forge/llvmlite-feedstock/git/refs{/sha}",
      "git_tags_url":"https://api.github.com/repos/conda-forge/llvmlite-feedstock/git/tags{/sha}",
      "git_url":"git://github.com/conda-forge/llvmlite-feedstock.git",
      "has_downloads":true,
      "has_issues":true,
      "has_pages":false,
      "has_projects":true,
      "has_wiki":false,
      "homepage":null,
      "hooks_url":"https://api.github.com/repos/conda-forge/llvmlite-feedstock/hooks",
      "html_url":"https://github.com/conda-forge/llvmlite-feedstock",
      "id":114010207,
      "issue_comment_url":"https://api.github.com/repos/conda-forge/llvmlite-feedstock/issues/comments{/number}",
      "issue_events_url":"https://api.github.com/repos/conda-forge/llvmlite-feedstock/issues/events{/number}",
      "issues_url":"https://api.github.com/repos/conda-forge/llvmlite-feedstock/issues{/number}",
      "keys_url":"https://api.github.com/repos/conda-forge/llvmlite-feedstock/keys{/key_id}",
      "labels_url":"https://api.github.com/repos/conda-forge/llvmlite-feedstock/labels{/name}",
      "language":"Shell",
      "languages_url":"https://api.github.com/repos/conda-forge/llvmlite-feedstock/languages",
      "license":{
       "key":"bsd-3-clause",
       "name":"BSD 3-Clause \"New\" or \"Revised\" License",
       "node_id":"MDc6TGljZW5zZTU=",
       "spdx_id":"BSD-3-Clause",
       "url":"https://api.github.com/licenses/bsd-3-clause"
      },
      "merges_url":"https://api.github.com/repos/conda-forge/llvmlite-feedstock/merges",
      "milestones_url":"https://api.github.com/repos/conda-forge/llvmlite-feedstock/milestones{/number}",
      "mirror_url":null,
      "name":"llvmlite-feedstock",
      "node_id":"MDEwOlJlcG9zaXRvcnkxMTQwMTAyMDc=",
      "notifications_url":"https://api.github.com/repos/conda-forge/llvmlite-feedstock/notifications{?since,all,participating}",
      "open_issues":4,
      "open_issues_count":4,
      "owner":{
       "avatar_url":"https://avatars3.githubusercontent.com/u/11897326?v=4",
       "events_url":"https://api.github.com/users/conda-forge/events{/privacy}",
       "followers_url":"https://api.github.com/users/conda-forge/followers",
       "following_url":"https://api.github.com/users/conda-forge/following{/other_user}",
       "gists_url":"https://api.github.com/users/conda-forge/gists{/gist_id}",
       "gravatar_id":"",
       "html_url":"https://github.com/conda-forge",
       "id":11897326,
       "login":"conda-forge",
       "node_id":"MDEyOk9yZ2FuaXphdGlvbjExODk3MzI2",
       "organizations_url":"https://api.github.com/users/conda-forge/orgs",
       "received_events_url":"https://api.github.com/users/conda-forge/received_events",
       "repos_url":"https://api.github.com/users/conda-forge/repos",
       "site_admin":false,
       "starred_url":"https://api.github.com/users/conda-forge/starred{/owner}{/repo}",
       "subscriptions_url":"https://api.github.com/users/conda-forge/subscriptions",
       "type":"Organization",
       "url":"https://api.github.com/users/conda-forge"
      },
      "private":false,
      "pulls_url":"https://api.github.com/repos/conda-forge/llvmlite-feedstock/pulls{/number}",
      "pushed_at":"2020-01-03T19:14:34Z",
      "releases_url":"https://api.github.com/repos/conda-forge/llvmlite-feedstock/releases{/id}",
      "size":88,
      "ssh_url":"git@github.com:conda-forge/llvmlite-feedstock.git",
      "stargazers_count":0,
      "stargazers_url":"https://api.github.com/repos/conda-forge/llvmlite-feedstock/stargazers",
      "statuses_url":"https://api.github.com/repos/conda-forge/llvmlite-feedstock/statuses/{sha}",
      "subscribers_url":"https://api.github.com/repos/conda-forge/llvmlite-feedstock/subscribers",
      "subscription_url":"https://api.github.com/repos/conda-forge/llvmlite-feedstock/subscription",
      "svn_url":"https://github.com/conda-forge/llvmlite-feedstock",
      "tags_url":"https://api.github.com/repos/conda-forge/llvmlite-feedstock/tags",
      "teams_url":"https://api.github.com/repos/conda-forge/llvmlite-feedstock/teams",
      "trees_url":"https://api.github.com/repos/conda-forge/llvmlite-feedstock/git/trees{/sha}",
      "updated_at":"2019-11-02T01:03:58Z",
      "url":"https://api.github.com/repos/conda-forge/llvmlite-feedstock",
      "watchers":0,
      "watchers_count":0
     },
     "sha":"36410608d13100d48179f2e5744eb8e935e2abfc",
     "user":{
      "avatar_url":"https://avatars3.githubusercontent.com/u/11897326?v=4",
      "events_url":"https://api.github.com/users/conda-forge/events{/privacy}",
      "followers_url":"https://api.github.com/users/conda-forge/followers",
      "following_url":"https://api.github.com/users/conda-forge/following{/other_user}",
      "gists_url":"https://api.github.com/users/conda-forge/gists{/gist_id}",
      "gravatar_id":"",
      "html_url":"https://github.com/conda-forge",
      "id":11897326,
      "login":"conda-forge",
      "node_id":"MDEyOk9yZ2FuaXphdGlvbjExODk3MzI2",
      "organizations_url":"https://api.github.com/users/conda-forge/orgs",
      "received_events_url":"https://api.github.com/users/conda-forge/received_events",
      "repos_url":"https://api.github.com/users/conda-forge/repos",
      "site_admin":false,
      "starred_url":"https://api.github.com/users/conda-forge/starred{/owner}{/repo}",
      "subscriptions_url":"https://api.github.com/users/conda-forge/subscriptions",
      "type":"Organization",
      "url":"https://api.github.com/users/conda-forge"
     }
    },
    "body":"It is very likely that the current package version for this feedstock is out of date.\nNotes for merging this PR:\n1. Feel free to push to the bot's branch to update this PR if needed.\n2. The bot will almost always only open one PR per version.\nChecklist before merging this PR:\n- [ ] Dependencies have been updated if changed\n- [ ] Tests have passed \n- [ ] Updated license if changed and `license_file` is packaged \n\nNote that the bot will stop issuing PRs if more than 3 Version bump PRs generated by the bot are open. If you don't want to package a particular version please close the PR.\n\n\nIf this PR was opened in error or needs to be updated please add the `bot-rerun` label to this PR. The bot will close this PR and schedule another one.\n\n<sub>This PR was created by the [cf-regro-autotick-bot](https://github.com/regro/cf-scripts).\nThe **cf-regro-autotick-bot** is a service to automatically track the dependency graph, migrate packages, and propose package version updates for conda-forge. If you would like a local version of this bot, you might consider using [rever](https://regro.github.io/rever-docs/). Rever is a tool for automating software releases and forms the backbone of the bot's conda-forge PRing capability. Rever is both conda (`conda install -c conda-forge rever`) and pip (`pip install re-ver`) installable.\nFinally, feel free to drop us a line if there are any [issues](https://github.com/regro/cf-scripts/issues)!\nThis PR was generated by https://circleci.com/gh/regro/circle_worker/13378, please use this URL for debugging</sub>\n\nHere is a list of all the pending dependencies (and their versions) for this repo. Please double check all dependencies before merging.\n\n| Name | Upstream Version | Current Version |\n|:----:|:----------------:|:---------------:|\n|cmake|3.16.2|[![Anaconda-Server Badge](https://img.shields.io/conda/vn/conda-forge/cmake.svg)](https://anaconda.org/conda-forge/cmake)|\n|llvmdev|10-init|[![Anaconda-Server Badge](https://img.shields.io/conda/vn/conda-forge/llvmdev.svg)](https://anaconda.org/conda-forge/llvmdev)|\n",
    "body_html":"<p>It is very likely that the current package version for this feedstock is out of date.<br>\nNotes for merging this PR:</p>\n<ol>\n<li>Feel free to push to the bot's branch to update this PR if needed.</li>\n<li>The bot will almost always only open one PR per version.<br>\nChecklist before merging this PR:</li>\n</ol>\n<ul class=\"contains-task-list\">\n<li class=\"task-list-item\"><input type=\"checkbox\" id=\"\" disabled=\"\" class=\"task-list-item-checkbox\"> Dependencies have been updated if changed</li>\n<li class=\"task-list-item\"><input type=\"checkbox\" id=\"\" disabled=\"\" class=\"task-list-item-checkbox\"> Tests have passed</li>\n<li class=\"task-list-item\"><input type=\"checkbox\" id=\"\" disabled=\"\" class=\"task-list-item-checkbox\"> Updated license if changed and <code>license_file</code> is packaged</li>\n</ul>\n<p>Note that the bot will stop issuing PRs if more than 3 Version bump PRs generated by the bot are open. If you don't want to package a particular version please close the PR.</p>\n<p>If this PR was opened in error or needs to be updated please add the <code>bot-rerun</code> label to this PR. The bot will close this PR and schedule another one.</p>\n<p><sub>This PR was created by the <a href=\"https://github.com/regro/cf-scripts\">cf-regro-autotick-bot</a>.<br>\nThe <strong>cf-regro-autotick-bot</strong> is a service to automatically track the dependency graph, migrate packages, and propose package version updates for conda-forge. If you would like a local version of this bot, you might consider using <a href=\"https://regro.github.io/rever-docs/\" rel=\"nofollow\">rever</a>. Rever is a tool for automating software releases and forms the backbone of the bot's conda-forge PRing capability. Rever is both conda (<code>conda install -c conda-forge rever</code>) and pip (<code>pip install re-ver</code>) installable.<br>\nFinally, feel free to drop us a line if there are any <a href=\"https://github.com/regro/cf-scripts/issues\">issues</a>!<br>\nThis PR was generated by <a rel=\"nofollow\" href=\"https://circleci.com/gh/regro/circle_worker/13378\">https://circleci.com/gh/regro/circle_worker/13378</a>, please use this URL for debugging</sub></p>\n<p>Here is a list of all the pending dependencies (and their versions) for this repo. Please double check all dependencies before merging.</p>\n<table>\n<thead>\n<tr>\n<th align=\"center\">Name</th>\n<th align=\"center\">Upstream Version</th>\n<th align=\"center\">Current Version</th>\n</tr>\n</thead>\n<tbody>\n<tr>\n<td align=\"center\">cmake</td>\n<td align=\"center\">3.16.2</td>\n<td align=\"center\"><a href=\"https://anaconda.org/conda-forge/cmake\" rel=\"nofollow\"><img src=\"https://camo.githubusercontent.com/0216a2a248acc93e72719696c04b9f474b131ccd/68747470733a2f2f696d672e736869656c64732e696f2f636f6e64612f766e2f636f6e64612d666f7267652f636d616b652e737667\" alt=\"Anaconda-Server Badge\" data-canonical-src=\"https://img.shields.io/conda/vn/conda-forge/cmake.svg\" style=\"max-width:100%;\"></a></td>\n</tr>\n<tr>\n<td align=\"center\">llvmdev</td>\n<td align=\"center\">10-init</td>\n<td align=\"center\"><a href=\"https://anaconda.org/conda-forge/llvmdev\" rel=\"nofollow\"><img src=\"https://camo.githubusercontent.com/78caa287f6ff45e038f51d3d35e0f19485e30d09/68747470733a2f2f696d672e736869656c64732e696f2f636f6e64612f766e2f636f6e64612d666f7267652f6c6c766d6465762e737667\" alt=\"Anaconda-Server Badge\" data-canonical-src=\"https://img.shields.io/conda/vn/conda-forge/llvmdev.svg\" style=\"max-width:100%;\"></a></td>\n</tr>\n</tbody>\n</table>",
    "body_text":"It is very likely that the current package version for this feedstock is out of date.\nNotes for merging this PR:\n\nFeel free to push to the bot's branch to update this PR if needed.\nThe bot will almost always only open one PR per version.\nChecklist before merging this PR:\n\n\n Dependencies have been updated if changed\n Tests have passed\n Updated license if changed and license_file is packaged\n\nNote that the bot will stop issuing PRs if more than 3 Version bump PRs generated by the bot are open. If you don't want to package a particular version please close the PR.\nIf this PR was opened in error or needs to be updated please add the bot-rerun label to this PR. The bot will close this PR and schedule another one.\nThis PR was created by the cf-regro-autotick-bot.\nThe cf-regro-autotick-bot is a service to automatically track the dependency graph, migrate packages, and propose package version updates for conda-forge. If you would like a local version of this bot, you might consider using rever. Rever is a tool for automating software releases and forms the backbone of the bot's conda-forge PRing capability. Rever is both conda (conda install -c conda-forge rever) and pip (pip install re-ver) installable.\nFinally, feel free to drop us a line if there are any issues!\nThis PR was generated by https://circleci.com/gh/regro/circle_worker/13378, please use this URL for debugging\nHere is a list of all the pending dependencies (and their versions) for this repo. Please double check all dependencies before merging.\n\n\n\nName\nUpstream Version\nCurrent Version\n\n\n\n\ncmake\n3.16.2\n\n\n\nllvmdev\n10-init",
    "changed_files":3,
    "closed_at":null,
    "comments":0,
    "comments_url":"https://api.github.com/repos/conda-forge/llvmlite-feedstock/issues/24/comments",
    "commits":2,
    "commits_url":"https://api.github.com/repos/conda-forge/llvmlite-feedstock/pulls/24/commits",
    "created_at":"2020-01-03T22:04:18Z",
    "deletions":4,
    "diff_url":"https://github.com/conda-forge/llvmlite-feedstock/pull/24.diff",
    "head":{
     "label":"regro-cf-autotick-bot:0.31.0",
     "ref":"0.31.0",
     "repo":{
      "archive_url":"https://api.github.com/repos/regro-cf-autotick-bot/llvmlite-feedstock/{archive_format}{/ref}",
      "archived":false,
      "assignees_url":"https://api.github.com/repos/regro-cf-autotick-bot/llvmlite-feedstock/assignees{/user}",
      "blobs_url":"https://api.github.com/repos/regro-cf-autotick-bot/llvmlite-feedstock/git/blobs{/sha}",
      "branches_url":"https://api.github.com/repos/regro-cf-autotick-bot/llvmlite-feedstock/branches{/branch}",
      "clone_url":"https://github.com/regro-cf-autotick-bot/llvmlite-feedstock.git",
      "collaborators_url":"https://api.github.com/repos/regro-cf-autotick-bot/llvmlite-feedstock/collaborators{/collaborator}",
      "comments_url":"https://api.github.com/repos/regro-cf-autotick-bot/llvmlite-feedstock/comments{/number}",
      "commits_url":"https://api.github.com/repos/regro-cf-autotick-bot/llvmlite-feedstock/commits{/sha}",
      "compare_url":"https://api.github.com/repos/regro-cf-autotick-bot/llvmlite-feedstock/compare/{base}...{head}",
      "contents_url":"https://api.github.com/repos/regro-cf-autotick-bot/llvmlite-feedstock/contents/{+path}",
      "contributors_url":"https://api.github.com/repos/regro-cf-autotick-bot/llvmlite-feedstock/contributors",
      "created_at":"2018-03-01T23:32:45Z",
      "default_branch":"master",
      "deployments_url":"https://api.github.com/repos/regro-cf-autotick-bot/llvmlite-feedstock/deployments",
      "description":"A conda-smithy repository for llvmlite.",
      "disabled":false,
      "downloads_url":"https://api.github.com/repos/regro-cf-autotick-bot/llvmlite-feedstock/downloads",
      "events_url":"https://api.github.com/repos/regro-cf-autotick-bot/llvmlite-feedstock/events",
      "fork":true,
      "forks":0,
      "forks_count":0,
      "forks_url":"https://api.github.com/repos/regro-cf-autotick-bot/llvmlite-feedstock/forks",
      "full_name":"regro-cf-autotick-bot/llvmlite-feedstock",
      "git_commits_url":"https://api.github.com/repos/regro-cf-autotick-bot/llvmlite-feedstock/git/commits{/sha}",
      "git_refs_url":"https://api.github.com/repos/regro-cf-autotick-bot/llvmlite-feedstock/git/refs{/sha}",
      "git_tags_url":"https://api.github.com/repos/regro-cf-autotick-bot/llvmlite-feedstock/git/tags{/sha}",
      "git_url":"git://github.com/regro-cf-autotick-bot/llvmlite-feedstock.git",
      "has_downloads":true,
      "has_issues":false,
      "has_pages":false,
      "has_projects":true,
      "has_wiki":false,
      "homepage":null,
      "hooks_url":"https://api.github.com/repos/regro-cf-autotick-bot/llvmlite-feedstock/hooks",
      "html_url":"https://github.com/regro-cf-autotick-bot/llvmlite-feedstock",
      "id":123504845,
      "issue_comment_url":"https://api.github.com/repos/regro-cf-autotick-bot/llvmlite-feedstock/issues/comments{/number}",
      "issue_events_url":"https://api.github.com/repos/regro-cf-autotick-bot/llvmlite-feedstock/issues/events{/number}",
      "issues_url":"https://api.github.com/repos/regro-cf-autotick-bot/llvmlite-feedstock/issues{/number}",
      "keys_url":"https://api.github.com/repos/regro-cf-autotick-bot/llvmlite-feedstock/keys{/key_id}",
      "labels_url":"https://api.github.com/repos/regro-cf-autotick-bot/llvmlite-feedstock/labels{/name}",
      "language":"Shell",
      "languages_url":"https://api.github.com/repos/regro-cf-autotick-bot/llvmlite-feedstock/languages",
      "license":{
       "key":"bsd-3-clause",
       "name":"BSD 3-Clause \"New\" or \"Revised\" License",
       "node_id":"MDc6TGljZW5zZTU=",
       "spdx_id":"BSD-3-Clause",
       "url":"https://api.github.com/licenses/bsd-3-clause"
      },
      "merges_url":"https://api.github.com/repos/regro-cf-autotick-bot/llvmlite-feedstock/merges",
      "milestones_url":"https://api.github.com/repos/regro-cf-autotick-bot/llvmlite-feedstock/milestones{/number}",
      "mirror_url":null,
      "name":"llvmlite-feedstock",
      "node_id":"MDEwOlJlcG9zaXRvcnkxMjM1MDQ4NDU=",
      "notifications_url":"https://api.github.com/repos/regro-cf-autotick-bot/llvmlite-feedstock/notifications{?since,all,participating}",
      "open_issues":0,
      "open_issues_count":0,
      "owner":{
       "avatar_url":"https://avatars3.githubusercontent.com/u/36490558?v=4",
       "events_url":"https://api.github.com/users/regro-cf-autotick-bot/events{/privacy}",
       "followers_url":"https://api.github.com/users/regro-cf-autotick-bot/followers",
       "following_url":"https://api.github.com/users/regro-cf-autotick-bot/following{/other_user}",
       "gists_url":"https://api.github.com/users/regro-cf-autotick-bot/gists{/gist_id}",
       "gravatar_id":"",
       "html_url":"https://github.com/regro-cf-autotick-bot",
       "id":36490558,
       "login":"regro-cf-autotick-bot",
       "node_id":"MDQ6VXNlcjM2NDkwNTU4",
       "organizations_url":"https://api.github.com/users/regro-cf-autotick-bot/orgs",
       "received_events_url":"https://api.github.com/users/regro-cf-autotick-bot/received_events",
       "repos_url":"https://api.github.com/users/regro-cf-autotick-bot/repos",
       "site_admin":false,
       "starred_url":"https://api.github.com/users/regro-cf-autotick-bot/starred{/owner}{/repo}",
       "subscriptions_url":"https://api.github.com/users/regro-cf-autotick-bot/subscriptions",
       "type":"User",
       "url":"https://api.github.com/users/regro-cf-autotick-bot"
      },
      "private":false,
      "pulls_url":"https://api.github.com/repos/regro-cf-autotick-bot/llvmlite-feedstock/pulls{/number}",
      "pushed_at":"2020-01-03T22:04:17Z",
      "releases_url":"https://api.github.com/repos/regro-cf-autotick-bot/llvmlite-feedstock/releases{/id}",
      "size":72,
      "ssh_url":"git@github.com:regro-cf-autotick-bot/llvmlite-feedstock.git",
      "stargazers_count":0,
      "stargazers_url":"https://api.github.com/repos/regro-cf-autotick-bot/llvmlite-feedstock/stargazers",
      "statuses_url":"https://api.github.com/repos/regro-cf-autotick-bot/llvmlite-feedstock/statuses/{sha}",
      "subscribers_url":"https://api.github.com/repos/regro-cf-autotick-bot/llvmlite-feedstock/subscribers",
      "subscription_url":"https://api.github.com/repos/regro-cf-autotick-bot/llvmlite-feedstock/subscription",
      "svn_url":"https://github.com/regro-cf-autotick-bot/llvmlite-feedstock",
      "tags_url":"https://api.github.com/repos/regro-cf-autotick-bot/llvmlite-feedstock/tags",
      "teams_url":"https://api.github.com/repos/regro-cf-autotick-bot/llvmlite-feedstock/teams",
      "trees_url":"https://api.github.com/repos/regro-cf-autotick-bot/llvmlite-feedstock/git/trees{/sha}",
      "updated_at":"2018-03-01T23:32:47Z",
      "url":"https://api.github.com/repos/regro-cf-autotick-bot/llvmlite-feedstock",
      "watchers":0,
      "watchers_count":0
     },
     "sha":"7c2612e82c3254f72de3003484d71c5640c6053f",
     "user":{
      "avatar_url":"https://avatars3.githubusercontent.com/u/36490558?v=4",
      "events_url":"https://api.github.com/users/regro-cf-autotick-bot/events{/privacy}",
      "followers_url":"https://api.github.com/users/regro-cf-autotick-bot/followers",
      "following_url":"https://api.github.com/users/regro-cf-autotick-bot/following{/other_user}",
      "gists_url":"https://api.github.com/users/regro-cf-autotick-bot/gists{/gist_id}",
      "gravatar_id":"",
      "html_url":"https://github.com/regro-cf-autotick-bot",
      "id":36490558,
      "login":"regro-cf-autotick-bot",
      "node_id":"MDQ6VXNlcjM2NDkwNTU4",
      "organizations_url":"https://api.github.com/users/regro-cf-autotick-bot/orgs",
      "received_events_url":"https://api.github.com/users/regro-cf-autotick-bot/received_events",
      "repos_url":"https://api.github.com/users/regro-cf-autotick-bot/repos",
      "site_admin":false,
      "starred_url":"https://api.github.com/users/regro-cf-autotick-bot/starred{/owner}{/repo}",
      "subscriptions_url":"https://api.github.com/users/regro-cf-autotick-bot/subscriptions",
      "type":"User",
      "url":"https://api.github.com/users/regro-cf-autotick-bot"
     }
    },
    "html_url":"https://github.com/conda-forge/llvmlite-feedstock/pull/24",
    "id":359137567,
    "issue_url":"https://api.github.com/repos/conda-forge/llvmlite-feedstock/issues/24",
    "labels":[],
    "locked":false,
    "maintainer_can_modify":true,
    "merge_commit_sha":null,
    "mergeable":null,
    "mergeable_state":"unknown",
    "merged":false,
    "merged_at":null,
    "merged_by":null,
    "milestone":null,
    "node_id":"MDExOlB1bGxSZXF1ZXN0MzU5MTM3NTY3",
    "number":24,
    "patch_url":"https://github.com/conda-forge/llvmlite-feedstock/pull/24.patch",
    "rebaseable":null,
    "requested_reviewers":[
     {
      "avatar_url":"https://avatars3.githubusercontent.com/u/4314261?v=4",
      "events_url":"https://api.github.com/users/souravsingh/events{/privacy}",
      "followers_url":"https://api.github.com/users/souravsingh/followers",
      "following_url":"https://api.github.com/users/souravsingh/following{/other_user}",
      "gists_url":"https://api.github.com/users/souravsingh/gists{/gist_id}",
      "gravatar_id":"",
      "html_url":"https://github.com/souravsingh",
      "id":4314261,
      "login":"souravsingh",
      "node_id":"MDQ6VXNlcjQzMTQyNjE=",
      "organizations_url":"https://api.github.com/users/souravsingh/orgs",
      "received_events_url":"https://api.github.com/users/souravsingh/received_events",
      "repos_url":"https://api.github.com/users/souravsingh/repos",
      "site_admin":false,
      "starred_url":"https://api.github.com/users/souravsingh/starred{/owner}{/repo}",
      "subscriptions_url":"https://api.github.com/users/souravsingh/subscriptions",
      "type":"User",
      "url":"https://api.github.com/users/souravsingh"
     }
    ],
    "requested_teams":[],
    "review_comment_url":"https://api.github.com/repos/conda-forge/llvmlite-feedstock/pulls/comments{/number}",
    "review_comments":0,
    "review_comments_url":"https://api.github.com/repos/conda-forge/llvmlite-feedstock/pulls/24/comments",
    "state":"open",
    "statuses_url":"https://api.github.com/repos/conda-forge/llvmlite-feedstock/statuses/7c2612e82c3254f72de3003484d71c5640c6053f",
    "title":"llvmlite v0.31.0",
    "updated_at":"2020-01-03T22:04:18Z",
    "url":"https://api.github.com/repos/conda-forge/llvmlite-feedstock/pulls/24",
    "user":{
     "avatar_url":"https://avatars3.githubusercontent.com/u/36490558?v=4",
     "events_url":"https://api.github.com/users/regro-cf-autotick-bot/events{/privacy}",
     "followers_url":"https://api.github.com/users/regro-cf-autotick-bot/followers",
     "following_url":"https://api.github.com/users/regro-cf-autotick-bot/following{/other_user}",
     "gists_url":"https://api.github.com/users/regro-cf-autotick-bot/gists{/gist_id}",
     "gravatar_id":"",
     "html_url":"https://github.com/regro-cf-autotick-bot",
     "id":36490558,
     "login":"regro-cf-autotick-bot",
     "node_id":"MDQ6VXNlcjM2NDkwNTU4",
     "organizations_url":"https://api.github.com/users/regro-cf-autotick-bot/orgs",
     "received_events_url":"https://api.github.com/users/regro-cf-autotick-bot/received_events",
     "repos_url":"https://api.github.com/users/regro-cf-autotick-bot/repos",
     "site_admin":false,
     "starred_url":"https://api.github.com/users/regro-cf-autotick-bot/starred{/owner}{/repo}",
     "subscriptions_url":"https://api.github.com/users/regro-cf-autotick-bot/subscriptions",
     "type":"User",
     "url":"https://api.github.com/users/regro-cf-autotick-bot"
    }
   },
   "data":{
    "bot_rerun":false,
    "migrator_name":"Version",
    "migrator_version":0,
    "version":"0.31.0"
   },
   "keys":[
    "bot_rerun",
    "migrator_name",
    "migrator_version",
    "version"
   ]
  }
 ],
 "bad":false,
 "conda-forge.yml":{
  "compiler_stack":"comp7",
  "max_py_ver":"37",
  "max_r_ver":"35",
  "provider":{
   "win":"azure"
  }
 },
 "feedstock_name":"llvmlite",
 "hash_type":"sha256",
 "meta_yaml":{
  "about":{
   "dev_url":"https://github.com/numba/llvmlite",
   "doc_url":"http://llvmlite.pydata.org/",
   "home":"http://llvmlite.pydata.org",
   "license":"BSD-2-clause",
   "license_file":"LICENSE",
   "summary":"A lightweight LLVM python binding for writing JIT compilers."
  },
  "build":{
   "number":"1"
  },
  "extra":{
   "recipe-maintainers":[
    "souravsingh",
    "souravsingh",
    "souravsingh"
   ]
  },
  "package":{
   "name":"llvmlite",
   "version":"0.30.0"
  },
  "requirements":{
   "build":[
    "vs2017_win-64",
    "cmake",
    "c_compiler_stub",
    "cxx_compiler_stub",
    "make",
    "c_compiler_stub",
    "cxx_compiler_stub",
    "make"
   ],
   "host":[
    "python",
    "llvmdev 8.0.*",
    "llvm 8.0.*",
    "python",
    "llvmdev 8.0.*",
    "llvm 8.0.*",
    "zlib",
    "python",
    "llvmdev 8.0.*",
    "llvm 8.0.*",
    "zlib"
   ],
   "run":[
    "python",
    "python",
    "python"
   ]
  },
  "source":{
   "fn":"llvmlite-0.30.0.tar.gz",
   "sha256":"4eaa398d4cafb76e2d8f30ca6ab875039a1023c91e7a690c6ddec20e58bb9a07",
   "url":"https://pypi.io/packages/source/l/llvmlite/llvmlite-0.30.0.tar.gz"
  },
  "test":{
   "commands":[
    "python -m llvmlite.tests",
    "python -m llvmlite.tests",
    "python -m llvmlite.tests"
   ],
   "imports":[
    "llvmlite",
    "llvmlite.binding",
    "llvmlite",
    "llvmlite.binding",
    "llvmlite",
    "llvmlite.binding"
   ]
  }
 },
 "name":"llvmlite",
 "new_version":"0.31.0",
 "pinning_version":"2019.12.18",
 "raw_meta_yaml":"{% set name = \"llvmlite\" %}\n{% set version = \"0.30.0\" %}\n{% set sha256 = \"4eaa398d4cafb76e2d8f30ca6ab875039a1023c91e7a690c6ddec20e58bb9a07\" %}\n\npackage:\n  name: {{ name|lower }}\n  version: {{ version }}\n\nsource:\n  fn: {{ name }}-{{ version }}.tar.gz\n  # don't use github generated tar-ball as the sha256 value may not be stable\n  url: https://pypi.io/packages/source/{{ name[0] }}/{{ name }}/{{ name }}-{{ version }}.tar.gz\n  sha256: {{ sha256 }}\n\nbuild:\n  number: 1\n  skip: true  # [win and py==27]\n\nrequirements:\n  build:\n    - {{ compiler('c') }}    # [unix or (win and py==27)]\n    - {{ compiler('cxx') }}  # [unix or (win and py==27)]\n    - vs2017_win-64          # [win64 and py>27]\n    - vs2017_win-32          # [win32 and py>27]\n    # The DLL build uses cmake on Windows\n    - cmake                  # [win]\n    - make                   # [unix]\n  host:\n    - python\n    - llvmdev 8.0.*\n    - llvm 8.0.*\n    - enum34          # [py27]\n    # llvmdev is built with libz compression support\n    - zlib            # [unix]\n  run:\n    - python\n    - enum34          # [py27]\n\ntest:\n  imports:\n    - llvmlite\n    - llvmlite.binding\n  commands:\n    - python -m llvmlite.tests\n\nabout:\n  home: http://llvmlite.pydata.org\n  license: BSD-2-clause\n  license_file: LICENSE\n  summary: A lightweight LLVM python binding for writing JIT compilers.\n  doc_url: http://llvmlite.pydata.org/\n  dev_url: https://github.com/numba/llvmlite\n\nextra:\n  recipe-maintainers:\n    - souravsingh\n",
 "req":{
  "__set__":true,
  "elements":[
   "c_compiler_stub",
   "cmake",
   "cxx_compiler_stub",
   "llvm",
   "llvmdev",
   "make",
   "python",
   "vs2017_win-64",
   "zlib"
  ]
 },
 "smithy_version":"3.6.5",
 "url":"https://pypi.io/packages/source/l/llvmlite/llvmlite-0.29.0.tar.gz",
 "version":"0.30.0"
}