{
 "PRed":[
  {
   "data":{
    "bot_rerun":false,
    "migrator_name":"Version",
    "migrator_version":0,
    "version":"4.2.2"
   },
   "keys":[
    "bot_rerun",
    "migrator_name",
    "migrator_version",
    "version"
   ]
  },
  {
   "PR":{
    "__lazy_json__":"pr_json/216431200.json"
   },
   "data":{
    "bot_rerun":false,
    "migrator_name":"Version",
    "migrator_version":0,
    "version":"5.0"
   },
   "keys":[
    "bot_rerun",
    "migrator_name",
    "migrator_version",
    "version"
   ]
  },
  {
   "PR":{
    "__lazy_json__":"pr_json/217517250.json"
   },
   "data":{
    "bot_rerun":false,
    "migrator_name":"CompilerRebuild",
    "migrator_version":1,
    "name":"Python 3.7, GCC 7, R 3.5.1, openBLAS 0.3.2"
   },
   "keys":[
    "bot_rerun",
    "migrator_name",
    "migrator_version",
    "name"
   ]
  },
  {
   "PR":{
    "__lazy_json__":"pr_json/223385852.json"
   },
   "data":{
    "bot_rerun":false,
    "migrator_name":"Version",
    "migrator_version":0,
    "version":"5.1"
   },
   "keys":[
    "bot_rerun",
    "migrator_name",
    "migrator_version",
    "version"
   ]
  },
  {
   "PR":{
    "__lazy_json__":"pr_json/227372868.json"
   },
   "data":{
    "bot_rerun":false,
    "migrator_name":"Version",
    "migrator_version":0,
    "version":"5.1.1"
   },
   "keys":[
    "bot_rerun",
    "migrator_name",
    "migrator_version",
    "version"
   ]
  },
  {
   "PR":{
    "__lazy_json__":"pr_json/238500817.json"
   },
   "data":{
    "bot_rerun":false,
    "migrator_name":"Version",
    "migrator_version":0,
    "version":"5.1.2"
   },
   "keys":[
    "bot_rerun",
    "migrator_name",
    "migrator_version",
    "version"
   ]
  },
  {
   "PR":{
    "__lazy_json__":"pr_json/266908756.json"
   },
   "data":{
    "bot_rerun":false,
    "migrator_name":"Version",
    "migrator_version":0,
    "version":"5.2"
   },
   "keys":[
    "bot_rerun",
    "migrator_name",
    "migrator_version",
    "version"
   ]
  }
 ],
 "bad":{
  "code":404,
  "exception":"HTTP Error 404: Not Found",
  "traceback":[
   "Traceback (most recent call last):",
   "  File \"/root/repo/cf-scripts/conda_forge_tick/auto_tick.xsh\", line 682, in main",
   "    hash_type=attrs.get('hash_type', 'sha256'))",
   "  File \"/root/repo/cf-scripts/conda_forge_tick/auto_tick.xsh\", line 98, in run",
   "    migrate_return = migrator.migrate(recipe_dir, attrs, **kwargs)",
   "  File \"/root/repo/cf-scripts/conda_forge_tick/migrators.xsh\", line 465, in migrate",
   "    new_patterns = self.get_hash_patterns('meta.yaml', urls, hash_type)",
   "  File \"/root/repo/cf-scripts/conda_forge_tick/migrators.xsh\", line 382, in get_hash_patterns",
   "    hash = hash_url(url, hash_type)",
   "  File \"/opt/conda/envs/run_env/lib/python3.7/site-packages/rever/tools.xsh\", line 207, in hash_url",
   "    for b in stream_url_progress(url, verb='Hashing', quiet=quiet):",
   "  File \"/opt/conda/envs/run_env/lib/python3.7/site-packages/rever/tools.xsh\", line 179, in stream_url_progress",
   "    with urllib.request.urlopen(url) as f:",
   "  File \"/opt/conda/envs/run_env/lib/python3.7/urllib/request.py\", line 222, in urlopen",
   "    return opener.open(url, data, timeout)",
   "  File \"/opt/conda/envs/run_env/lib/python3.7/urllib/request.py\", line 531, in open",
   "    response = meth(req, response)",
   "  File \"/opt/conda/envs/run_env/lib/python3.7/urllib/request.py\", line 641, in http_response",
   "    'http', request, response, code, msg, hdrs)",
   "  File \"/opt/conda/envs/run_env/lib/python3.7/urllib/request.py\", line 563, in error",
   "    result = self._call_chain(*args)",
   "  File \"/opt/conda/envs/run_env/lib/python3.7/urllib/request.py\", line 503, in _call_chain",
   "    result = func(*args)",
   "  File \"/opt/conda/envs/run_env/lib/python3.7/urllib/request.py\", line 755, in http_error_302",
   "    return self.parent.open(new, timeout=req.timeout)",
   "  File \"/opt/conda/envs/run_env/lib/python3.7/urllib/request.py\", line 531, in open",
   "    response = meth(req, response)",
   "  File \"/opt/conda/envs/run_env/lib/python3.7/urllib/request.py\", line 641, in http_response",
   "    'http', request, response, code, msg, hdrs)",
   "  File \"/opt/conda/envs/run_env/lib/python3.7/urllib/request.py\", line 563, in error",
   "    result = self._call_chain(*args)",
   "  File \"/opt/conda/envs/run_env/lib/python3.7/urllib/request.py\", line 503, in _call_chain",
   "    result = func(*args)",
   "  File \"/opt/conda/envs/run_env/lib/python3.7/urllib/request.py\", line 755, in http_error_302",
   "    return self.parent.open(new, timeout=req.timeout)",
   "  File \"/opt/conda/envs/run_env/lib/python3.7/urllib/request.py\", line 531, in open",
   "    response = meth(req, response)",
   "  File \"/opt/conda/envs/run_env/lib/python3.7/urllib/request.py\", line 641, in http_response",
   "    'http', request, response, code, msg, hdrs)",
   "  File \"/opt/conda/envs/run_env/lib/python3.7/urllib/request.py\", line 569, in error",
   "    return self._call_chain(*args)",
   "  File \"/opt/conda/envs/run_env/lib/python3.7/urllib/request.py\", line 503, in _call_chain",
   "    result = func(*args)",
   "  File \"/opt/conda/envs/run_env/lib/python3.7/urllib/request.py\", line 649, in http_error_default",
   "    raise HTTPError(req.full_url, code, msg, hdrs, fp)",
   "urllib.error.HTTPError: HTTP Error 404: Not Found",
   ""
  ],
  "url":"https://files.pythonhosted.org/packages/source/p/pyobjc-core/pyobjc-core-5.3.zip"
 },
 "conda-forge.yml":{
  "compiler_stack":"comp7",
  "max_py_ver":"37",
  "max_r_ver":"35"
 },
 "feedstock_name":"pyobjc-core",
 "hash_type":"sha256",
 "meta_yaml":{
  "about":{
   "home":"http://pyobjc.sourceforge.net/",
   "license":"MIT",
   "license_family":"MIT",
   "license_file":"License.txt",
   "summary":"Python<->ObjC Interoperability Module"
  },
  "build":{
   "number":"0",
   "script":"python setup.py install --single-version-externally-managed --record record.txt",
   "skip":true
  },
  "extra":{
   "recipe-maintainers":[
    "kastman",
    "kastman",
    "kastman"
   ]
  },
  "package":{
   "name":"pyobjc-core",
   "version":"5.2"
  },
  "requirements":{
   "build":[
    "python",
    "setuptools",
    "python",
    "setuptools",
    "python",
    "setuptools"
   ],
   "run":[
    "python",
    "setuptools",
    "python",
    "setuptools",
    "python",
    "setuptools"
   ]
  },
  "source":{
   "fn":"pyobjc-core-5.2.tar.gz",
   "sha256":"cd13a2e9be890064a6dd11db7790bbf38502350c532a9a9d05511abb8683b8ea",
   "url":"https://pypi.io/packages/source/p/pyobjc-core/pyobjc-core-5.2.tar.gz"
  },
  "test":{
   "imports":[
    "PyObjCTools",
    "objc",
    "PyObjCTools",
    "objc",
    "PyObjCTools",
    "objc"
   ]
  }
 },
 "name":"pyobjc-core",
 "new_version":"5.3",
 "pinning_version":"2019.03.17",
 "raw_meta_yaml":"{% set name = \"pyobjc-core\" %}\n{% set version = \"5.2\" %}\n{% set sha256 = \"cd13a2e9be890064a6dd11db7790bbf38502350c532a9a9d05511abb8683b8ea\" %}\n\npackage:\n  name: {{ name }}\n  version: {{ version }}\n\nsource:\n  fn: {{ name }}-{{ version }}.tar.gz\n  url: https://pypi.io/packages/source/{{ name[0] }}/{{ name }}/{{ name }}-{{ version }}.tar.gz\n  sha256: {{ sha256 }}\n\nbuild:\n  number: 0\n  skip: true  # [not osx]\n  script: python setup.py install --single-version-externally-managed --record record.txt\n\nrequirements:\n  build:\n    - python\n    - setuptools\n\n  run:\n    - python\n    - setuptools\n\ntest:\n  imports:\n    - PyObjCTools\n    - objc\n\nabout:\n  home: http://pyobjc.sourceforge.net/\n  license: MIT\n  summary: 'Python<->ObjC Interoperability Module'\n  license_family: MIT\n  license_file: License.txt\n\nextra:\n  recipe-maintainers:\n    - kastman\n",
 "req":{
  "__set__":true,
  "elements":[
   "python",
   "setuptools"
  ]
 },
 "smithy_version":"3.3.2",
 "url":"https://pypi.io/packages/source/p/pyobjc-core/pyobjc-core-5.2.tar.gz",
 "version":"5.2"
}