{
 "builtin":{
  "__set__":true,
  "elements":[
   "__future__",
   "codecs",
   "collections",
   "errno",
   "functools",
   "glob",
   "imp",
   "importlib",
   "inspect",
   "itertools",
   "optparse",
   "os",
   "pathlib",
   "pprint",
   "re",
   "shutil",
   "subprocess",
   "sys",
   "tempfile",
   "test",
   "types",
   "unittest"
  ]
 },
 "questionable":{
  "__set__":true,
  "elements":[
   "ansible",
   "pathlib2",
   "pkg_resources",
   "setuptools_scm"
  ]
 },
 "relative":{
  "__set__":true,
  "elements":[
   "rules"
  ]
 },
 "required":{
  "__set__":true,
  "elements":[
   "ansible",
   "ansiblelint",
   "pyyaml",
   "ruamel.yaml",
   "rules",
   "setuptools_scm",
   "six"
  ]
 }
}