{
 "builtin":{
  "__set__":true,
  "elements":[
   "collections",
   "distutils",
   "functools",
   "io",
   "json",
   "os",
   "pathlib",
   "pipes",
   "re",
   "shlex",
   "subprocess",
   "sys",
   "warnings"
  ]
 },
 "questionable":{
  "__set__":true,
  "elements":[
   "setuptools",
   "wheel"
  ]
 },
 "relative":{
  "__set__":true,
  "elements":[
   "_version",
   "handlers",
   "loader"
  ]
 },
 "required":{
  "__set__":true,
  "elements":[
   "jupyter_core",
   "notebook",
   "setupbase",
   "setuptools",
   "tornado"
  ]
 }
}