{
 "builtin":{
  "__set__":true,
  "elements":[
   "__future__",
   "argparse",
   "binascii",
   "collections",
   "contextlib",
   "copy",
   "datetime",
   "functools",
   "io",
   "itertools",
   "logging",
   "os",
   "re",
   "struct",
   "sys",
   "tempfile",
   "time",
   "unittest",
   "warnings"
  ]
 },
 "questionable":{
  "__set__":true,
  "elements":[
   "h5py",
   "mock",
   "ordereddict",
   "pandas",
   "scipy",
   "thermocouples_reference"
  ]
 },
 "relative":{
  "__set__":true,
  "elements":[
   "tdms",
   "version",
   "writer"
  ]
 },
 "required":{
  "__set__":true,
  "elements":[
   "hypothesis",
   "nptdms",
   "numpy",
   "pytest",
   "setuptools"
  ]
 }
}