{
 "builtin":{
  "__set__":true,
  "elements":[
   "__future__",
   "atexit",
   "distutils",
   "io",
   "math",
   "multiprocessing",
   "numbers",
   "os",
   "pickle",
   "pprint",
   "re",
   "readline",
   "rlcompleter",
   "signal",
   "sys",
   "tempfile",
   "threading",
   "time",
   "unittest"
  ]
 },
 "questionable":{
  "__set__":true,
  "elements":[
   "ESMP",
   "PyQt4",
   "PyQt5",
   "cdms2",
   "cdtime",
   "esmpcontrol",
   "pipedviewer",
   "pyferret",
   "regrid2d",
   "regrid3d",
   "scipy",
   "shapefile"
  ]
 },
 "required":{
  "__set__":true,
  "elements":[
   "ESMP",
   "PyQt4",
   "PyQt5",
   "StringIO",
   "eofanalysis",
   "esmpcontrol",
   "numpy",
   "pipedviewer",
   "pyferret",
   "regrid2d",
   "regrid3d",
   "scipy",
   "shapefile",
   "shapefile_readxyz",
   "shapefile_readxyzval"
  ]
 }
}