{
 "builtin":{
  "__set__":true,
  "elements":[
   "__future__",
   "asyncio",
   "base64",
   "configparser",
   "distutils",
   "errno",
   "io",
   "json",
   "os",
   "pathlib",
   "re",
   "subprocess",
   "sys",
   "typing"
  ]
 },
 "questionable":{
  "__set__":true,
  "elements":[
   "ConfigParser",
   "cx_Freeze",
   "pyppeteer",
   "setuptools"
  ]
 },
 "relative":{
  "__set__":true,
  "elements":[
   "_version",
   "patch_pyppeteer",
   "pyppeteer_pdf",
   "replace_mathjax"
  ]
 },
 "required":{
  "__set__":true,
  "elements":[
   "certifi",
   "click",
   "litereval",
   "pyppeteer",
   "setuptools",
   "versioneer"
  ]
 }
}