{
 "builtin":{
  "__set__":true,
  "elements":[
   "atexit",
   "builtins",
   "collections",
   "configparser",
   "ctypes",
   "enum",
   "functools",
   "inspect",
   "ipaddress",
   "json",
   "multiprocessing",
   "operator",
   "os",
   "pickle",
   "re",
   "socket",
   "subprocess",
   "sys",
   "tempfile",
   "time",
   "uuid",
   "warnings"
  ]
 },
 "questionable":{
  "__set__":true,
  "elements":[
   "llvmlite",
   "numba",
   "numpy",
   "rbc",
   "tblib"
  ]
 },
 "relative":{
  "__set__":true,
  "elements":[
   "client",
   "dispatcher",
   "errors",
   "irtools",
   "npy_mathimpl",
   "omnisci_array",
   "remotejit",
   "server",
   "targetinfo",
   "test_thrift_multiplexed",
   "thrift",
   "types",
   "typesystem",
   "utils"
  ]
 },
 "required":{
  "__set__":true,
  "elements":[
   "docutils",
   "llvmlite",
   "netifaces",
   "numba",
   "numpy",
   "pymapd",
   "pytest",
   "rbc",
   "setuptools",
   "six",
   "thriftpy2"
  ]
 }
}