{
 "builtin":{
  "__set__":true,
  "elements":[
   "__future__",
   "argparse",
   "array",
   "ast",
   "atexit",
   "base64",
   "cProfile",
   "code",
   "codecs",
   "collections",
   "contextlib",
   "copy",
   "dataclasses",
   "datetime",
   "difflib",
   "doctest",
   "errno",
   "filecmp",
   "functools",
   "getpass",
   "gzip",
   "hashlib",
   "importlib",
   "io",
   "itertools",
   "json",
   "logging",
   "math",
   "multiprocessing",
   "numbers",
   "operator",
   "os",
   "pickle",
   "platform",
   "pprint",
   "random",
   "re",
   "readline",
   "rlcompleter",
   "shlex",
   "shutil",
   "socket",
   "stat",
   "string",
   "struct",
   "subprocess",
   "sys",
   "tarfile",
   "tempfile",
   "textwrap",
   "threading",
   "time",
   "timeit",
   "unittest",
   "uuid",
   "warnings",
   "zipfile"
  ]
 },
 "questionable":{
  "__set__":true,
  "elements":[
   "compiler",
   "configobj",
   "h5py",
   "keyring",
   "mpi4py",
   "numpy",
   "pandas",
   "passlib",
   "pymongo",
   "signac",
   "tables"
  ]
 },
 "relative":{
  "__set__":true,
  "elements":[
   "_version",
   "attrdict",
   "collection",
   "common",
   "config",
   "configobj",
   "connection",
   "contrib",
   "core",
   "crypt",
   "database",
   "db",
   "dict_manager",
   "diff",
   "errors",
   "filterparse",
   "hashing",
   "import_export",
   "indexing",
   "job",
   "linked_view",
   "mpipool",
   "project",
   "schema",
   "sync",
   "synceddict",
   "syncutil",
   "utility",
   "v0_to_v1",
   "validate",
   "version"
  ]
 },
 "required":{
  "__set__":true,
  "elements":[
   "click",
   "deprecation",
   "filelock",
   "git",
   "packaging",
   "pandas",
   "psutil",
   "pymongo",
   "pytest",
   "ruamel.yaml",
   "setuptools",
   "signac",
   "sphinx_rtd_theme",
   "test_h5store",
   "test_job",
   "test_project",
   "tqdm"
  ]
 }
}