{
 "builtin":{
  "__set__":true,
  "elements":[
   "__future__",
   "bisect",
   "cmath",
   "collections",
   "copy",
   "doctest",
   "functools",
   "inspect",
   "io",
   "json",
   "math",
   "os",
   "pprint",
   "random",
   "re",
   "string",
   "sys",
   "types",
   "warnings",
   "xml",
   "zipfile"
  ]
 },
 "questionable":{
  "__set__":true,
  "elements":[
   "CoolProp",
   "ipython",
   "matplotlib",
   "numpy",
   "pint",
   "py3Dmol",
   "rdkit",
   "scipy",
   "sympy",
   "ternary",
   "thermo"
  ]
 },
 "relative":{
  "__set__":true,
  "elements":[
   "acentric",
   "activity",
   "chemical",
   "combustion",
   "coolprop",
   "critical",
   "datasheet",
   "dipole",
   "dippr",
   "electrochem",
   "elements",
   "environment",
   "eos",
   "eos_mix",
   "heat_capacity",
   "identifiers",
   "interface",
   "joback",
   "law",
   "lennard_jones",
   "miscdata",
   "mixture",
   "permittivity",
   "phase_change",
   "property_package",
   "reaction",
   "refractivity",
   "safety",
   "solubility",
   "stream",
   "thermal_conductivity",
   "triple",
   "unifac",
   "utils",
   "vapor_pressure",
   "virial",
   "viscosity",
   "volume"
  ]
 },
 "required":{
  "__set__":true,
  "elements":[
   "fluids",
   "matplotlib",
   "numpy",
   "pandas",
   "pytest",
   "scipy",
   "setuptools",
   "sphinx",
   "thermo"
  ]
 }
}