{
 "builtin":{
  "__set__":true,
  "elements":[
   "__future__",
   "abc",
   "asyncio",
   "collections",
   "contextlib",
   "copy",
   "datetime",
   "glob",
   "hashlib",
   "inspect",
   "itertools",
   "logging",
   "os",
   "platform",
   "pprint",
   "re",
   "shlex",
   "shutil",
   "subprocess",
   "sys",
   "tarfile",
   "tempfile",
   "textwrap",
   "time",
   "unittest",
   "uuid",
   "warnings"
  ]
 },
 "questionable":{
  "__set__":true,
  "elements":[
   "databroker",
   "pandas",
   "pyFAI",
   "xpdacq",
   "xpdan",
   "xpdsim"
  ]
 },
 "relative":{
  "__set__":true,
  "elements":[
   "beamtime",
   "conftest",
   "glbl",
   "tools",
   "utils",
   "validated_dict",
   "xpdacq",
   "xpdacq_conf",
   "yamldict"
  ]
 },
 "required":{
  "__set__":true,
  "elements":[
   "bluesky",
   "ipython",
   "jinja2",
   "numpy",
   "ophyd",
   "pandas",
   "pkg_resources",
   "pyFAI",
   "pytest",
   "pyyaml",
   "recommonmark",
   "setuptools",
   "xpdacq",
   "xpdan",
   "xpdconf",
   "xpdsim",
   "xpdtools"
  ]
 }
}